{
    "title": "最新消息",
    "link": "https://spec.site.nthu.edu.tw/p/403-1247-7151-1.php?Lang=zh-tw",
    "language": "zh-tw",
    "department": "師資培育中心特殊教育中心",
    "articles": [
        {
            "title": "115/08/14「應用行為分析入門手冊及社會與情緒學習行動方案專書導讀」研習",
            "link": "https://spec.site.nthu.edu.tw/p/406-1247-306522,r7151.php?Lang=zh-tw",
            "date": ""
        },
        {
            "title": "115/05/29「自閉症大專生情緒行為障礙與社交技巧課程」研習",
            "link": "https://spec.site.nthu.edu.tw/p/406-1247-306438,r7151.php?Lang=zh-tw",
            "date": ""
        },
        {
            "title": "115/7/3「自我管理(含時間管理、金錢管理、健康管理等)－讓光透入那未癒的生命裂縫」研習",
            "link": "https://spec.site.nthu.edu.tw/p/406-1247-306248,r7151.php?Lang=zh-tw",
            "date": ""
        },
        {
            "title": "115/8/6「正向行為支持—三個層級正向行為支持的架構與內涵」研習",
            "link": "https://spec.site.nthu.edu.tw/p/406-1247-306244,r7151.php?Lang=zh-tw",
            "date": ""
        },
        {
            "title": "115/7/23「融合教育與校園支持系統建立—讓差異也能自在」研習",
            "link": "https://spec.site.nthu.edu.tw/p/406-1247-306243,r7151.php?Lang=zh-tw",
            "date": ""
        },
        {
            "title": "115/7/21「個別化支持計畫(ISP)與個別化轉銜計畫(ITP)的擬定、修正與執行－身心障礙學生整體支持服務的落實」研習",
            "link": "https://spec.site.nthu.edu.tw/p/406-1247-305774,r7151.php?Lang=zh-tw",
            "date": ""
        },
        {
            "title": "115/7/8「身心障礙學生能力與特殊需求評估」暨「個別化支持計畫(ISP)與個別化轉銜計畫(ITP)簡介與擬訂」研習",
            "link": "https://spec.site.nthu.edu.tw/p/406-1247-305630,r7151.php?Lang=zh-tw",
            "date": ""
        },
        {
            "title": "115/6/9「身心障礙學生自我決策與自立生活準備－談心智障礙者的支持」研習",
            "link": "https://spec.site.nthu.edu.tw/p/406-1247-305326,r7151.php?Lang=zh-tw",
            "date": ""
        },
        {
            "title": "115/5/27「輔助科技的運用－AI工具流融入資源教室實務議題工作坊」研習",
            "link": "https://spec.site.nthu.edu.tw/p/406-1247-305325,r7151.php?Lang=zh-tw",
            "date": ""
        },
        {
            "title": "【2026 TSSE 國際學術研討會｜論文徵稿】(8/28截止)",
            "link": "https://spec.site.nthu.edu.tw/p/406-1247-303340,r7151.php?Lang=zh-tw",
            "date": ""
        },
        {
            "title": "高師特教中心-徵稿資訊 2026全國特殊教育教學實務學術研討會徵稿（3/8截止）",
            "link": "https://spec.site.nthu.edu.tw/p/406-1247-302661,r7151.php?Lang=zh-tw",
            "date": ""
        },
        {
            "title": "115年度教育部委託國立清華大學辦理 大專校院特殊教育專責單位輔導人員特殊教育研習： 「自傳及履歷撰寫面試須知指導- 職涯伴飛×履歷與面試實戰」",
            "link": "https://spec.site.nthu.edu.tw/p/406-1247-301449,r7151.php?Lang=zh-tw",
            "date": ""
        }
    ]
}