{
    "title": "最新消息 News  - 國立清華大學竹師教育學院",
    "link": "https://ec.site.nthu.edu.tw/p/403-1584-70-1.php?Lang=zh-tw",
    "language": "zh-tw",
    "department": "竹師教育學院",
    "articles": [
        {
            "title": "【開放報名】🌟COE English Corner | 竹師教育學院英語角🌟",
            "link": "https://ec.site.nthu.edu.tw/p/406-1584-306074,r70.php?Lang=zh-tw",
            "date": ""
        },
        {
            "title": "【獎學金】竹師教育學院曾維垣教授清寒獎學金",
            "link": "https://ec.site.nthu.edu.tw/p/406-1584-305290,r70.php?Lang=zh-tw",
            "date": ""
        },
        {
            "title": "【公告】「國際交流大使」甄選錄取名單與後續事項說明",
            "link": "https://ec.site.nthu.edu.tw/p/406-1584-305154,r70.php?Lang=zh-tw",
            "date": ""
        },
        {
            "title": "【公告】國際交流大使決選面試通知、簡報繳交提醒與面試順序",
            "link": "https://ec.site.nthu.edu.tw/p/406-1584-304971,r70.php?Lang=zh-tw",
            "date": ""
        },
        {
            "title": "【竹師教育學院】2026 Fall 韓國春川教育大學出國交換計畫",
            "link": "https://ec.site.nthu.edu.tw/p/406-1584-304830,r70.php?Lang=zh-tw",
            "date": ""
        },
        {
            "title": "【開放教師報名】3/19 國際學者午餐交流會｜Networking Lunch ✨",
            "link": "https://ec.site.nthu.edu.tw/p/406-1584-304757,r70.php?Lang=zh-tw",
            "date": ""
        },
        {
            "title": "【開放報名】國際學者講座 International Scholar Series : Dr. Benedek Kurdi",
            "link": "https://ec.site.nthu.edu.tw/p/406-1584-304668,r70.php?Lang=zh-tw",
            "date": ""
        },
        {
            "title": "國立清華大學竹師教育學院學生出國交流獎勵辦法",
            "link": "https://ec.site.nthu.edu.tw/p/406-1584-304620,r70.php?Lang=zh-tw",
            "date": ""
        },
        {
            "title": "【公告】出國參加國際學術研討會發表論文交流獎勵申請（截止：2026年5月22日）",
            "link": "https://ec.site.nthu.edu.tw/p/406-1584-304622,r70.php?Lang=zh-tw",
            "date": ""
        },
        {
            "title": "有關大型廢棄物清運即報廢由事務組統一辦理",
            "link": "https://ec.site.nthu.edu.tw/p/406-1584-304325,r70.php?Lang=zh-tw",
            "date": ""
        },
        {
            "title": "【活動資訊轉發】AI教育人才培育工作坊",
            "link": "https://ec.site.nthu.edu.tw/p/406-1584-304216,r70.php?Lang=zh-tw",
            "date": ""
        },
        {
            "title": "【活動資訊轉發】2026 華德福教育系列論壇",
            "link": "https://ec.site.nthu.edu.tw/p/406-1584-304168,r70.php?Lang=zh-tw",
            "date": ""
        }
    ]
}