{
    "title": "banner",
    "link": "https://cls.site.nthu.edu.tw/p/403-1469-8083-1.php?Lang=zh-tw",
    "language": "zh-tw",
    "department": "生命科學暨醫學院",
    "articles": [
        {
            "title": "《賀》醫學科學系陳令儀教授團隊獲第二十二屆國家新創獎  (主題：NTHU-3促進腦傷後神經修復及功能回復)",
            "link": "https://cls.site.nthu.edu.tw/p/406-1469-299687,r8083.php?Lang=zh-tw",
            "date": "2025-11-28"
        },
        {
            "title": "「國立清華大學生命科學暨醫學院pitch talk競賽」決賽結果公告",
            "link": "https://cls.site.nthu.edu.tw/p/406-1469-299237,r8083.php?Lang=zh-tw",
            "date": "2025-11-20"
        },
        {
            "title": "恭喜生資所郭力中同學參加 2025 MOPM 多體學與精準醫學聯合會議，榮獲論文海報獎！",
            "link": "https://cls.site.nthu.edu.tw/p/406-1469-299111,r8083.php?Lang=zh-tw",
            "date": "2025-11-18"
        },
        {
            "title": "恭賀分生所博士生阮紅榮、李庭慧於2025台灣病毒暨疫苗學會獲獎",
            "link": "https://cls.site.nthu.edu.tw/p/406-1469-298114,r8083.php?Lang=zh-tw",
            "date": "2025-11-03"
        },
        {
            "title": "2025.10.1 感謝【康霈生技股份有限公司】慷慨捐贈本院生圖空間整修經費",
            "link": "https://cls.site.nthu.edu.tw/p/406-1469-296551,r8083.php?Lang=zh-tw",
            "date": "2025-10-02"
        },
        {
            "title": "吃還是逃？清華破解果蠅大腦嗅覺密碼",
            "link": "https://cls.site.nthu.edu.tw/p/406-1469-293445,r8083.php?Lang=zh-tw",
            "date": "2025-08-07"
        },
        {
            "title": "恭喜本院教師於2025.8.1起升等Congratulations to our faculty member on their promotion, effective August 1, 2025.",
            "link": "https://cls.site.nthu.edu.tw/p/406-1469-293162,r8083.php?Lang=zh-tw",
            "date": "2025-08-01"
        },
        {
            "title": "恭喜 生科系 李庭慧同學(王慧菁教授指導)及陳彥臻同學(郭立園教授指導)  及生命科學暨醫學院學士班 陳昱文同學(汪宏達教授指導)  榮獲113年度國科會大專學生研究創作獎！",
            "link": "https://cls.site.nthu.edu.tw/p/406-1469-291459,r8083.php?Lang=zh-tw",
            "date": "2025-07-01"
        }
    ]
}